datalake_common/__init__.py
datalake_common/errors.py
datalake_common/metadata.py
datalake_common/conf.py
datalake_common/record.py
datalake_common/tests/test_record.py
datalake_common/tests/__init__.py
datalake_common/tests/conftest.py
datalake_common/tests/test_metadata.py
datalake_common-0.9.0.dist-info/RECORD
datalake_common-0.9.0.dist-info/METADATA
datalake_common-0.9.0.dist-info/DESCRIPTION.rst
datalake_common-0.9.0.dist-info/WHEEL
datalake_common-0.9.0.dist-info/top_level.txt
datalake_common-0.9.0.dist-info/metadata.json
