Metadata-Version: 2.0
Name: datalake-common
Version: 0.9.0
Summary: common datalake parts
Home-page: https://github.com/planetlabs/datalake-common
Author: Brian Cavagnolo
Author-email: brian@planet.com
License: UNKNOWN
Platform: UNKNOWN
Requires-Dist: python-dateutil (>=2.4.2)
Requires-Dist: pytz (>=2015.4)
Requires-Dist: pyver (>=1.0.18)
Requires-Dist: simplejson (>=3.3.1)
Provides-Extra: test
Requires-Dist: pytest (==2.7.2); extra == 'test'
Requires-Dist: pip (==7.1.0); extra == 'test'
Requires-Dist: wheel (==0.24.0); extra == 'test'
Provides-Extra: s3
Requires-Dist: boto (>=2.38.0); extra == 's3'
Provides-Extra: test-s3
Requires-Dist: moto (==0.4.12); extra == 'test-s3'
